CHANGELOG.md
LICENSE.txt
README.md
valarpy/__init__.py
valarpy/connection.py
valarpy/metamodel.py
valarpy/model.py
valarpy-2.2.0.dist-info/LICENSE.txt
valarpy-2.2.0.dist-info/WHEEL
valarpy-2.2.0.dist-info/METADATA
valarpy-2.2.0.dist-info/RECORD
