Metadata-Version: 2.1
Name: valarpy
Version: 2.2.0
Summary: Python ORM to talk to Valar.
Home-page: https://github.com/dmyersturnbull/valarpy
License: Apache-2.0
Keywords: valar,orm,zebrafish
Author: Douglas Myers-Turnbull
Maintainer: Douglas Myers-Turnbull
Requires-Python: >=3.8,<4
Classifier: Development Status :: 5 - Production/Stable
Classifier: Intended Audience :: Developers
Classifier: License :: OSI Approved :: Apache Software License
Classifier: Natural Language :: English
Classifier: Operating System :: OS Independent
Classifier: Programming Language :: Python :: 3
Classifier: Programming Language :: Python :: 3 :: Only
Classifier: Programming Language :: Python :: 3.8
Classifier: Topic :: Database
Classifier: Topic :: Scientific/Engineering :: Bio-Informatics
Classifier: Topic :: Scientific/Engineering :: Chemistry
Classifier: Topic :: Software Development :: Libraries :: Python Modules
Provides-Extra: dev
Requires-Dist: PyMySQL (>=0.9,<1.0)
Requires-Dist: pandas (>=1,<2)
Requires-Dist: peewee (>=3.13,<4.0)
Project-URL: CI, https://github.com/dmyersturnbull/valarpy/actions
Project-URL: Documentation, https://valarpy.readthedocs.io
Project-URL: Download, https://pypi.org/project/valarpy/
Project-URL: Issues, https://github.com/dmyersturnbull/valarpy/issues
Project-URL: Repository, https://github.com/dmyersturnbull/valarpy
